acycling_digraph_problem/__init__.py
acycling_digraph_problem/edge.py
acycling_digraph_problem/graph.py
acycling_digraph_problem/main.py
acycling_digraph_problem/parser.py
acycling_digraph_problem/star_graph.py
acycling_digraph_problem/utils.py
acycling_digraph_problem-0.1.7.dist-info/entry_points.txt
acycling_digraph_problem-0.1.7.dist-info/WHEEL
acycling_digraph_problem-0.1.7.dist-info/METADATA
acycling_digraph_problem-0.1.7.dist-info/RECORD
